cssfix/__init__.py
cssfix-2.1.0.dist-info/licenses/LICENSE
cssfix-2.1.0.dist-info/METADATA
cssfix-2.1.0.dist-info/WHEEL
cssfix-2.1.0.dist-info/top_level.txt
cssfix-2.1.0.dist-info/RECORD
