Metadata-Version: 2.4
Name: cssfix
Version: 2.1.0
Summary: Simple CSS optimizer module for merging class properties
Home-page: https://github.com/seekiii/cssfix
Author: seekii
Author-email: seekii.official@example.com
License: MIT
Keywords: css optimizer cssfix css merge
Classifier: Programming Language :: Python :: 3
Classifier: Operating System :: OS Independent
Requires-Python: >=3.6
License-File: LICENSE
Dynamic: author
Dynamic: author-email
Dynamic: classifier
Dynamic: description
Dynamic: description-content-type
Dynamic: home-page
Dynamic: keywords
Dynamic: license
Dynamic: license-file
Dynamic: requires-python
Dynamic: summary
